odoo8_addon_sale_order_ubl-8.0.1.0.0.99.dev12-nspkg.pth
odoo_addons/sale_order_ubl/README.rst
odoo_addons/sale_order_ubl/__init__.py
odoo_addons/sale_order_ubl/__openerp__.py
odoo_addons/sale_order_ubl/i18n/sale_order_ubl.pot
odoo_addons/sale_order_ubl/models/__init__.py
odoo_addons/sale_order_ubl/models/report.py
odoo_addons/sale_order_ubl/models/sale.py
odoo_addons/sale_order_ubl/static/description/icon.png
odoo_addons/sale_order_ubl/tests/__init__.py
odoo_addons/sale_order_ubl/tests/test_ubl_generate.py
odoo8_addon_sale_order_ubl-8.0.1.0.0.99.dev12.dist-info/METADATA
odoo8_addon_sale_order_ubl-8.0.1.0.0.99.dev12.dist-info/WHEEL
odoo8_addon_sale_order_ubl-8.0.1.0.0.99.dev12.dist-info/namespace_packages.txt
odoo8_addon_sale_order_ubl-8.0.1.0.0.99.dev12.dist-info/top_level.txt
odoo8_addon_sale_order_ubl-8.0.1.0.0.99.dev12.dist-info/RECORD
